hyo2.qc-3.5.12-py3.8-nspkg.pth
examples/__init__.py
examples/survey/__init__.py
examples/survey/ex_survey_project.py
examples/workground/__init__.py
examples/workground/ex_calc_nanmedian.py
examples/workground/ex_how_to_read_grid_layers.py
examples/workground/ex_read_kluster_zarr.py
hyo2/qc/__init__.py
hyo2/qc/chart/__init__.py
hyo2/qc/chart/project.py
hyo2/qc/chart/scan/__init__.py
hyo2/qc/chart/scan/base_scan.py
hyo2/qc/chart/scan/feature_scan_v3.py
hyo2/qc/chart/triangle/__init__.py
hyo2/qc/chart/triangle/base_triangle.py
hyo2/qc/chart/triangle/triangle_rule_v2.py
hyo2/qc/cli/__init__.py
hyo2/qc/cli/cli.py
hyo2/qc/cli/qctools_parser.py
hyo2/qc/common/__init__.py
hyo2/qc/common/default_logging.py
hyo2/qc/common/features.py
hyo2/qc/common/ftp.py
hyo2/qc/common/geodesy.py
hyo2/qc/common/project.py
hyo2/qc/common/s57_aux.py
hyo2/qc/common/testing.py
hyo2/qc/common/grid_callback/__init__.py
hyo2/qc/common/grid_callback/cli_grid_callback.py
hyo2/qc/common/grid_callback/qt_grid_callback.py
hyo2/qc/common/writers/__init__.py
hyo2/qc/common/writers/kml_writer.py
hyo2/qc/common/writers/s57_writer.py
hyo2/qc/common/writers/shp_writer.py
hyo2/qc/common/writers/svp_writer.py
hyo2/qc/qctools/__init__.py
hyo2/qc/qctools/__main__.py
hyo2/qc/qctools/gui.py
hyo2/qc/qctools/gui_settings.py
hyo2/qc/qctools/mainwin.py
hyo2/qc/qctools/media/LICENSE
hyo2/qc/qctools/media/QCTools.ico
hyo2/qc/qctools/media/add_files.png
hyo2/qc/qctools/media/add_folder.png
hyo2/qc/qctools/media/anomaly.png
hyo2/qc/qctools/media/app_icon.png
hyo2/qc/qctools/media/authors.png
hyo2/qc/qctools/media/back.png
hyo2/qc/qctools/media/bag.png
hyo2/qc/qctools/media/bag_checks.png
hyo2/qc/qctools/media/ccom.png
hyo2/qc/qctools/media/changes.png
hyo2/qc/qctools/media/chart.png
hyo2/qc/qctools/media/csar.png
hyo2/qc/qctools/media/designated.png
hyo2/qc/qctools/media/favicon.png
hyo2/qc/qctools/media/fliers.png
hyo2/qc/qctools/media/folder.png
hyo2/qc/qctools/media/grid_truncate.png
hyo2/qc/qctools/media/grid_xyz.png
hyo2.qc-3.5.12.dist-info/AUTHORS.rst
hyo2.qc-3.5.12.dist-info/LICENSE
hyo2.qc-3.5.12.dist-info/METADATA
hyo2.qc-3.5.12.dist-info/WHEEL
hyo2.qc-3.5.12.dist-info/entry_points.txt
hyo2.qc-3.5.12.dist-info/namespace_packages.txt
hyo2.qc-3.5.12.dist-info/top_level.txt
hyo2.qc-3.5.12.dist-info/RECORD
